ipyreactive/__init__.py
ipyreactive/_frontend.py
ipyreactive/_version.py
ipyreactive/example.py
ipyreactive/labextension/package.json
ipyreactive/labextension/static/480.c0a79913fe37a65914ef.js
ipyreactive/labextension/static/568.3662140165581aed36e5.js
ipyreactive/labextension/static/remoteEntry.dbeb6d47d186dea50600.js
ipyreactive/labextension/static/style.js
ipyreactive/labextension/static/third-party-licenses.json
ipyreactive/nbextension/extension.js
ipyreactive/nbextension/index.js
ipyreactive/nbextension/index.js.map
ipyreactive/tests/__init__.py
ipyreactive/tests/conftest.py
ipyreactive/tests/test_example.py
ipyreactive/tests/test_nbextension_path.py
ipyreactive-0.1.0.dev0.data/data/etc/jupyter/nbconfig/notebook.d/ipyreactive.json
ipyreactive-0.1.0.dev0.data/data/share/jupyter/labextensions/@datalayer/ipyreactive/install.json
ipyreactive-0.1.0.dev0.data/data/share/jupyter/labextensions/@datalayer/ipyreactive/package.json
ipyreactive-0.1.0.dev0.data/data/share/jupyter/labextensions/@datalayer/ipyreactive/static/480.c0a79913fe37a65914ef.js
ipyreactive-0.1.0.dev0.data/data/share/jupyter/labextensions/@datalayer/ipyreactive/static/568.3662140165581aed36e5.js
ipyreactive-0.1.0.dev0.data/data/share/jupyter/labextensions/@datalayer/ipyreactive/static/remoteEntry.dbeb6d47d186dea50600.js
ipyreactive-0.1.0.dev0.data/data/share/jupyter/labextensions/@datalayer/ipyreactive/static/style.js
ipyreactive-0.1.0.dev0.data/data/share/jupyter/labextensions/@datalayer/ipyreactive/static/third-party-licenses.json
ipyreactive-0.1.0.dev0.data/data/share/jupyter/nbextensions/ipyreactive/extension.js
ipyreactive-0.1.0.dev0.data/data/share/jupyter/nbextensions/ipyreactive/index.js
ipyreactive-0.1.0.dev0.data/data/share/jupyter/nbextensions/ipyreactive/index.js.map
ipyreactive-0.1.0.dev0.dist-info/LICENSE.txt
ipyreactive-0.1.0.dev0.dist-info/METADATA
ipyreactive-0.1.0.dev0.dist-info/WHEEL
ipyreactive-0.1.0.dev0.dist-info/top_level.txt
ipyreactive-0.1.0.dev0.dist-info/RECORD
